krisp/__init__.py
krisp/krisp_fasta/Amplicon.py
krisp/krisp_fasta/__init__.py
krisp/krisp_fasta/filterAlignments.py
krisp/krisp_fasta/intersectAmplicons.py
krisp/krisp_fasta/krisp_fasta.py
krisp/krisp_fasta/outputAlignments.py
krisp/krisp_fasta/shared.py
krisp/krisp_vcf/__init__.py
krisp/krisp_vcf/find_diag_var.py
krisp/krisp_vcf/krisp_vcf.py
krisp/krisp_vcf/print_align.py
krisp/kstream/__init__.py
krisp/kstream/kstream.py
krisp-0.1.6.dist-info/LICENSE
krisp-0.1.6.dist-info/METADATA
krisp-0.1.6.dist-info/WHEEL
krisp-0.1.6.dist-info/entry_points.txt
krisp-0.1.6.dist-info/top_level.txt
krisp-0.1.6.dist-info/RECORD
