Metadata-Version: 2.1
Name: krisp
Version: 0.1.6
Summary: A lightweight tool for finding diagnostic regions in whole genome data
Author-email: "Zachary S.L. Foster" <zacharyfoster1989@gmail.com>, "Andrew S. Tupper" <andrew.s.tupper@gmail.com>, "Niklaus J. Grunwald" <niklaus.grunwald@oregonstate.edu>
Maintainer-email: "Zachary S.L. Foster" <zacharyfoster1989@gmail.com>, "Andrew S. Tupper" <andrew.s.tupper@gmail.com>, "Niklaus J. Grunwald" <niklaus.grunwald@oregonstate.edu>
Project-URL: Homepage, https://github.com/grunwaldlab/krisp
Project-URL: Bug Tracker, https://github.com/grunwaldlab/krisp/issues
Classifier: Programming Language :: Python :: 3
Classifier: License :: OSI Approved :: MIT License
Classifier: Operating System :: OS Independent
Requires-Python: >=3.6
License-File: LICENSE
Requires-Dist: pysam
Requires-Dist: Bio
Requires-Dist: nltk
Requires-Dist: prettytable
Requires-Dist: pandas
Requires-Dist: primer3-py
Requires-Dist: colorama
